aiosmartoilgauge/__init__.py
aiosmartoilgauge/__main__.py
aiosmartoilgauge/client.py
aiosmartoilgauge/const.py
aiosmartoilgauge-1.0.3.dist-info/METADATA
aiosmartoilgauge-1.0.3.dist-info/WHEEL
aiosmartoilgauge-1.0.3.dist-info/top_level.txt
aiosmartoilgauge-1.0.3.dist-info/RECORD
